bethereum/__init__.py
bethereum-0.0.0.dist-info/METADATA
bethereum-0.0.0.dist-info/RECORD
bethereum-0.0.0.dist-info/WHEEL
bethereum-0.0.0.dist-info/top_level.txt
