Metadata-Version: 2.1
Name: bethereum
Version: 0.0.0
Summary: A python wrapper for the Bethereum SDK
Home-page: https://bethereum.com
Author: Sebastian Fischer
Author-email: python@bethereum.com
License: UNKNOWN
Platform: UNKNOWN
Classifier: Programming Language :: Python :: 3
Classifier: Operating System :: OS Independent
